{
  "_class": "shapePath",
  "booleanOperation": -1,
  "do_objectID": "4CBCEDC6-EC67-49A6-AF86-BF8CADA38F22",
  "edited": true,
  "exportOptions": {
    "_class": "exportOptions",
    "do_objectID": "96320553-B72F-4B7C-8AA7-CED0D823806C",
    "exportFormats": [
    ],
    "includedLayerIds": [
    ],
    "layerOptions": 0,
    "shouldTrim": false
  },
  "frame": {
    "_class": "rect",
    "constrainProportions": false,
    "do_objectID": "7732FBB4-6D51-490B-B2F0-FE23C531391F",
    "height": 35.00269596676139,
    "width": 79.95984613826658,
    "x": 0,
    "y": 2.273736754432316e-13
  },
  "isClosed": true,
  "isFixedToViewport": false,
  "isFlippedHorizontal": false,
  "isFlippedVertical": false,
  "isLocked": false,
  "isVisible": true,
  "layerListExpandedType": 0,
  "name": "photo_icon-4-path",
  "nameIsFixed": false,
  "pointRadiusBehaviour": 0,
  "points": [
    {
      "_class": "curvePoint",
      "cornerRadius": 0,
      "curveFrom": "{0.9916233536542306, 0.86957788989109619}",
      "curveMode": 1,
      "curveTo": "{0.9916233536542306, 0.86957788989109619}",
      "hasCurveFrom": false,
      "hasCurveTo": false,
      "point": "{0.9916233536542306, 0.86957788989109619}"
    },
    {
      "_class": "curvePoint",
      "cornerRadius": 0,
      "curveFrom": "{0.77936236314682372, 0.33431388690015212}",
      "curveMode": 4,
      "curveTo": "{0.7866454704844893, 0.35218917168501473}",
      "hasCurveFrom": true,
      "hasCurveTo": false,
      "point": "{0.7866454704844893, 0.35218917168501473}"
    },
    {
      "_class": "curvePoint",
      "cornerRadius": 0,
      "curveFrom": "{0.74778109316571939, 0.32402876768231775}",
      "curveMode": 2,
      "curveTo": "{0.76916082183401091, 0.3241370596141942}",
      "hasCurveFrom": true,
      "hasCurveTo": true,
      "point": "{0.75847095749986515, 0.3240829136482592}"
    },
    {
      "_class": "curvePoint",
      "cornerRadius": 0,
      "curveFrom": "{0.73024216035053402, 0.3519034794054976}",
      "curveMode": 4,
      "curveTo": "{0.73755989642357322, 0.33410215035528124}",
      "hasCurveFrom": false,
      "hasCurveTo": true,
      "point": "{0.73024216035053402, 0.3519034794054976}"
    },
    {
      "_class": "curvePoint",
      "cornerRadius": 0,
      "curveFrom": "{0.62656512243246587, 0.61359760744347513}",
      "curveMode": 1,
      "curveTo": "{0.62656512243246587, 0.61359760744347513}",
      "hasCurveFrom": false,
      "hasCurveTo": false,
      "point": "{0.62656512243246587, 0.61359760744347513}"
    },
    {
      "_class": "curvePoint",
      "cornerRadius": 0,
      "curveFrom": "{0.38900441039067951, 0.014971066967878938}",
      "curveMode": 4,
      "curveTo": "{0.3998263169494024, 0.041355971570043178}",
      "hasCurveFrom": true,
      "hasCurveTo": false,
      "point": "{0.3998263169494024, 0.041355971570043178}"
    },
    {
      "_class": "curvePoint",
      "cornerRadius": 0,
      "curveFrom": "{0.34222758881449356, 0}",
      "curveMode": 2,
      "curveTo": "{0.3738831134446633, 0}",
      "hasCurveFrom": true,
      "hasCurveTo": true,
      "point": "{0.35805535112957843, 0}"
    },
    {
      "_class": "curvePoint",
      "cornerRadius": 0,
      "curveFrom": "{0.31628438530975161, 0.041355971570043178}",
      "curveMode": 4,
      "curveTo": "{0.32710629186847451, 0.014971066967878938}",
      "hasCurveFrom": false,
      "hasCurveTo": true,
      "point": "{0.31628438530975161, 0.041355971570043178}"
    },
    {
      "_class": "curvePoint",
      "cornerRadius": 0,
      "curveFrom": "{-0.017007901845440109, 0.88329111930794024}",
      "curveMode": 4,
      "curveTo": "{0.013007163414315523, 0.80758266523581601}",
      "hasCurveFrom": true,
      "hasCurveTo": false,
      "point": "{0.013007163414315523, 0.80758266523581601}"
    },
    {
      "_class": "curvePoint",
      "cornerRadius": 0,
      "curveFrom": "{0.054778129234139508, 0.99985356935105385}",
      "curveMode": 4,
      "curveTo": "{0.0082547780815196981, 0.99985356935105385}",
      "hasCurveFrom": false,
      "hasCurveTo": true,
      "point": "{0.054778129234139508, 0.99985356935105385}"
    },
    {
      "_class": "curvePoint",
      "cornerRadius": 0,
      "curveFrom": "{0.97722092166498131, 1.0017804315466461}",
      "curveMode": 4,
      "curveTo": "{0.96335916720129233, 0.99985356935105385}",
      "hasCurveFrom": true,
      "hasCurveTo": false,
      "point": "{0.96335916720129233, 0.99985356935105385}"
    },
    {
      "_class": "curvePoint",
      "cornerRadius": 0,
      "curveFrom": "{1.0025738408925675, 0.92770686198745178}",
      "curveMode": 2,
      "curveTo": "{0.9902399741969834, 0.98455629109842002}",
      "hasCurveFrom": true,
      "hasCurveTo": true,
      "point": "{0.99640690754477546, 0.95613157654293912}"
    },
    {
      "_class": "curvePoint",
      "cornerRadius": 0,
      "curveFrom": "{0.99162335365422771, 0.86957788989109619}",
      "curveMode": 4,
      "curveTo": "{1.0006893750034211, 0.89360931154537082}",
      "hasCurveFrom": false,
      "hasCurveTo": true,
      "point": "{0.99162335365422771, 0.86957788989109619}"
    }
  ],
  "resizingConstraint": 63,
  "resizingType": 0,
  "rotation": 0,
  "shouldBreakMaskChain": false
}